flask_mail.py
flask_unchained/__init__.py
flask_unchained/_compat.py
flask_unchained/app_factory.py
flask_unchained/app_factory_hook.py
flask_unchained/cli.py
flask_unchained/click.py
flask_unchained/clips_pattern.py
flask_unchained/config.py
flask_unchained/constants.py
flask_unchained/di.py
flask_unchained/exceptions.py
flask_unchained/flask_unchained.py
flask_unchained/pytest.py
flask_unchained/routes.py
flask_unchained/string_utils.py
flask_unchained/unchained.py
flask_unchained/utils.py
flask_unchained/views.py
flask_unchained/_code_templates/project/.gitignore
flask_unchained/_code_templates/project/README.md
flask_unchained/_code_templates/project/__init__.py
flask_unchained/_code_templates/project/celery_app.py
flask_unchained/_code_templates/project/package.json
flask_unchained/_code_templates/project/requirements-dev.txt
flask_unchained/_code_templates/project/requirements.txt
flask_unchained/_code_templates/project/unchained_config.py
flask_unchained/_code_templates/project/wsgi.py
flask_unchained/_code_templates/project/app/__init__.py
flask_unchained/_code_templates/project/app/config.py
flask_unchained/_code_templates/project/app/routes.py
flask_unchained/_code_templates/project/app/extensions/__init__.py
flask_unchained/_code_templates/project/app/graphql/__init__.py
flask_unchained/_code_templates/project/app/graphql/mutations.py
flask_unchained/_code_templates/project/app/graphql/schema.py
flask_unchained/_code_templates/project/app/graphql/types.py
flask_unchained/_code_templates/project/app/models/__init__.py
flask_unchained/_code_templates/project/app/models/role.py
flask_unchained/_code_templates/project/app/models/user.py
flask_unchained/_code_templates/project/app/serializers/__init__.py
flask_unchained/_code_templates/project/app/services/__init__.py
flask_unchained/_code_templates/project/app/tasks/__init__.py
flask_unchained/_code_templates/project/app/templates/site/index.html
flask_unchained/_code_templates/project/app/views/__init__.py
Flask_Unchained-0.9.0.dist-info/LICENSE
Flask_Unchained-0.9.0.dist-info/METADATA
Flask_Unchained-0.9.0.dist-info/WHEEL
Flask_Unchained-0.9.0.dist-info/entry_points.txt
Flask_Unchained-0.9.0.dist-info/top_level.txt
Flask_Unchained-0.9.0.dist-info/RECORD
