Metadata-Version: 2.1
Name: Flask-Unchained
Version: 0.9.0
Summary: The quickest and easiest way to build large web apps and APIs with Flask and SQLAlchemy
Home-page: https://github.com/briancappello/flask-unchained
Author: Brian Cappello
License: MIT
Platform: UNKNOWN
Classifier: Development Status :: 3 - Alpha
Classifier: Environment :: Web Environment
Classifier: Framework :: Flask
Classifier: Intended Audience :: Developers
Classifier: License :: OSI Approved :: MIT License
Classifier: Programming Language :: Python :: 3
Classifier: Programming Language :: Python :: 3.7
Classifier: Programming Language :: Python :: 3.8
Classifier: Programming Language :: Python :: 3.9
Requires-Python: >=3.7
Requires-Dist: blinker (>=1.4)
Requires-Dist: click (>=8.0.1)
Requires-Dist: flask (>=2.0.1)
Requires-Dist: flask-babelex (>=0.9.4)
Requires-Dist: flask-wtf (>=0.15.1)
Requires-Dist: py-meta-utils (>=0.7.8)
Requires-Dist: pyterminalsize (>=0.1.0)
Requires-Dist: networkx (>=2.5)
Requires-Dist: werkzeug (>=2.0.1)
Requires-Dist: wtforms (>=2.3.3)
Requires-Dist: email-validator (>=1.1.2)
Provides-Extra: admin
Requires-Dist: flask-admin (>=1.5.7) ; extra == 'admin'
Provides-Extra: api
Requires-Dist: apispec (<5,>=4.5.0) ; extra == 'api'
Requires-Dist: apispec-webframeworks (>=0.5.2) ; extra == 'api'
Requires-Dist: flask-marshmallow (>=0.14.0) ; extra == 'api'
Requires-Dist: marshmallow (>=3.12.1) ; extra == 'api'
Requires-Dist: marshmallow-sqlalchemy (>=0.26) ; extra == 'api'
Provides-Extra: asyncio
Requires-Dist: quart (>=0.13.1) ; extra == 'asyncio'
Provides-Extra: celery
Requires-Dist: celery (>=4.4.7) ; extra == 'celery'
Requires-Dist: dill (>=0.3.3) ; extra == 'celery'
Provides-Extra: dev
Requires-Dist: coverage (>=4.5.1) ; extra == 'dev'
Requires-Dist: IPython (>=7.24.1) ; extra == 'dev'
Requires-Dist: pytest (>=4.6.5) ; extra == 'dev'
Requires-Dist: pytest-flask (>=1.0.0) ; extra == 'dev'
Requires-Dist: tox (>=3.5.2) ; extra == 'dev'
Provides-Extra: docs
Requires-Dist: IPython (>=7.24.1) ; extra == 'docs'
Requires-Dist: PyQt5 (>=5.15.1) ; extra == 'docs'
Requires-Dist: qtconsole (>=5.1.0) ; extra == 'docs'
Requires-Dist: sphinx (<3,>=2.4.4) ; extra == 'docs'
Requires-Dist: sphinx-click (>=1.4.0) ; extra == 'docs'
Requires-Dist: sphinx-material (>=0.0.32) ; extra == 'docs'
Requires-Dist: m2r (>=0.2.1) ; extra == 'docs'
Provides-Extra: graphene
Requires-Dist: graphql-core (<3,>=2.3.1) ; extra == 'graphene'
Requires-Dist: graphql-relay (<3,>=2.0.1) ; extra == 'graphene'
Requires-Dist: graphql-server-core (<2,>=1.2.0) ; extra == 'graphene'
Requires-Dist: flask-graphql (>=2.0) ; extra == 'graphene'
Requires-Dist: graphene (<3,>=2.1.8) ; extra == 'graphene'
Requires-Dist: graphene-sqlalchemy (<3,>=2.2.2) ; extra == 'graphene'
Provides-Extra: mail
Requires-Dist: beautifulsoup4 (>=4.9.3) ; extra == 'mail'
Requires-Dist: lxml (>=4.6.1) ; extra == 'mail'
Provides-Extra: oauth
Requires-Dist: Flask-OAuthlib (>=0.9.5) ; extra == 'oauth'
Provides-Extra: security
Requires-Dist: bcrypt (>=3.2.0) ; extra == 'security'
Requires-Dist: flask-login (>=0.5.0) ; extra == 'security'
Requires-Dist: flask-principal (>=0.4.0) ; extra == 'security'
Requires-Dist: itsdangerous (>=2.0.1) ; extra == 'security'
Requires-Dist: passlib (>=1.7.4) ; extra == 'security'
Provides-Extra: session
Requires-Dist: dill (>=0.3.3) ; extra == 'session'
Requires-Dist: flask-session (>=0.3.2) ; extra == 'session'
Provides-Extra: sqlalchemy
Requires-Dist: factory-boy (>=2.11.1) ; extra == 'sqlalchemy'
Requires-Dist: flask-migrate (>=2.5.3) ; extra == 'sqlalchemy'
Requires-Dist: flask-sqlalchemy-unchained (>=0.7.5) ; extra == 'sqlalchemy'
Requires-Dist: sqlalchemy (<2,>=1.3.24) ; extra == 'sqlalchemy'
Requires-Dist: sqlalchemy-unchained (>=0.11.1) ; extra == 'sqlalchemy'
Requires-Dist: wtforms-sqlalchemy (>=0.2) ; extra == 'sqlalchemy'
